harry_potter_yonier
